wavfile/__init__.py
wavfile/base.py
wavfile/chunk.py
wavfile/exception.py
wavfile/version.py
wavfile/wavread.py
wavfile/wavwrite.py
wavfile-4.6.1.dist-info/LICENSE.txt
wavfile-4.6.1.dist-info/METADATA
wavfile-4.6.1.dist-info/WHEEL
wavfile-4.6.1.dist-info/top_level.txt
wavfile-4.6.1.dist-info/RECORD
