Metadata-Version: 2.1
Name: wavfile
Version: 4.6.1
Summary: Read/write wave audio files to/from lists of native Python types.
Home-page: https://github.com/chummersone/pywavfile
Author: Christopher Hummersone
Author-email: chummersone@users.noreply.github.com
License: MIT
Classifier: License :: OSI Approved :: MIT License
Classifier: Programming Language :: Python :: 3
Classifier: Programming Language :: Python :: 3.7
Classifier: Programming Language :: Python :: 3.8
Classifier: Programming Language :: Python :: 3.9
Classifier: Programming Language :: Python :: 3.10
Classifier: Programming Language :: Python :: 3.11
Requires-Python: >=3.7
License-File: LICENSE.txt
